gcp_notifier/__init__.py
gcp_notifier-0.1.6.dist-info/licenses/LICENSE
gcp_notifier-0.1.6.dist-info/METADATA
gcp_notifier-0.1.6.dist-info/WHEEL
gcp_notifier-0.1.6.dist-info/top_level.txt
gcp_notifier-0.1.6.dist-info/RECORD
