Metadata-Version: 2.4
Name: gcp_notifier
Version: 0.1.6
Summary: A simple notification library for Google Cloud projects. Sends alerts via Email and Google Chat.
Author-email: Marcellus Montilla <marcellusmontilla@gmail.com>
License: MIT License
Project-URL: Homepage, https://github.com/marcellusmontilla/gcp_notifier
Project-URL: Repository, https://github.com/marcellusmontilla/gcp_notifier
Requires-Python: >=3.8
License-File: LICENSE
Requires-Dist: google-cloud-secret-manager
Requires-Dist: google-auth
Requires-Dist: requests
Provides-Extra: test
Requires-Dist: pytest; extra == "test"
Provides-Extra: async
Requires-Dist: aiosmtplib; extra == "async"
Requires-Dist: httpx; extra == "async"
Dynamic: license-file
